{
  "db_name": "PostgreSQL",
  "query": "\n        SELECT \n            id,\n            created_at,\n            token,\n            amount,\n            direction as \"direction: TransactionDirection\",\n            api_key_id::text\n        FROM transactions\n        ORDER BY created_at DESC\n        LIMIT $1 OFFSET $2\n        ",
  "describe": {
    "columns": [
      {
        "ordinal": 0,
        "name": "id",
        "type_info": "Uuid"
      },
      {
        "ordinal": 1,
        "name": "created_at",
        "type_info": "Timestamptz"
      },
      {
        "ordinal": 2,
        "name": "token",
        "type_info": "Text"
      },
      {
        "ordinal": 3,
        "name": "amount",
        "type_info": "Text"
      },
      {
        "ordinal": 4,
        "name": "direction: TransactionDirection",
        "type_info": {
          "Custom": {
            "name": "transaction_direction",
            "kind": {
              "Enum": [
                "Incoming",
                "Outgoing"
              ]
            }
          }
        }
      },
      {
        "ordinal": 5,
        "name": "api_key_id",
        "type_info": "Text"
      }
    ],
    "parameters": {
      "Left": [
        "Int8",
        "Int8"
      ]
    },
    "nullable": [
      false,
      false,
      false,
      false,
      false,
      null
    ]
  },
  "hash": "c3a093897321ce0d631b1ed28cf0963a4e3906321ca648b3e6328296909e2ca6"
}
