{
  "db_name": "PostgreSQL",
  "query": "\n            SELECT id, name, key, user_id, organization_id, last_used_at, expires_at, \n                   is_active, created_at, updated_at\n            FROM api_keys\n            ORDER BY created_at DESC\n            LIMIT $1 OFFSET $2\n            ",
  "describe": {
    "columns": [
      {
        "ordinal": 0,
        "name": "id",
        "type_info": "Uuid"
      },
      {
        "ordinal": 1,
        "name": "name",
        "type_info": "Varchar"
      },
      {
        "ordinal": 2,
        "name": "key",
        "type_info": "Varchar"
      },
      {
        "ordinal": 3,
        "name": "user_id",
        "type_info": "Varchar"
      },
      {
        "ordinal": 4,
        "name": "organization_id",
        "type_info": "Varchar"
      },
      {
        "ordinal": 5,
        "name": "last_used_at",
        "type_info": "Timestamptz"
      },
      {
        "ordinal": 6,
        "name": "expires_at",
        "type_info": "Timestamptz"
      },
      {
        "ordinal": 7,
        "name": "is_active",
        "type_info": "Bool"
      },
      {
        "ordinal": 8,
        "name": "created_at",
        "type_info": "Timestamptz"
      },
      {
        "ordinal": 9,
        "name": "updated_at",
        "type_info": "Timestamptz"
      }
    ],
    "parameters": {
      "Left": [
        "Int8",
        "Int8"
      ]
    },
    "nullable": [
      false,
      false,
      false,
      true,
      true,
      true,
      true,
      true,
      true,
      true
    ]
  },
  "hash": "fa134c372a2245803064af8a0d74392b152e2b7e073c76166faf80c87308b5a1"
}
